setup.py
pagerdutystats/__init__.py
pagerdutystats.egg-info/PKG-INFO
pagerdutystats.egg-info/SOURCES.txt
pagerdutystats.egg-info/dependency_links.txt
pagerdutystats.egg-info/entry_points.txt
pagerdutystats.egg-info/not-zip-safe
pagerdutystats.egg-info/requires.txt
pagerdutystats.egg-info/top_level.txt