Metadata-Version: 1.0
Name: pagerdutystats
Version: 0.0.1
Summary: Tool for calculating pager duty stats
Home-page: http://github.com/livefyre/pagerdutystats
Author: Nicholas Fowler
Author-email: nfowler@livefyre.com
License: MIT
Platform: UNKNOWN
